torchnaut/__init__.py
torchnaut/crps.py
torchnaut/epistemic.py
torchnaut/kde.py
torchnaut/mdn.py
torchnaut/utils.py
torchnaut-1.0.1.dist-info/licenses/LICENSE
torchnaut-1.0.1.dist-info/METADATA
torchnaut-1.0.1.dist-info/WHEEL
torchnaut-1.0.1.dist-info/top_level.txt
torchnaut-1.0.1.dist-info/RECORD
